setup.py
clockwatch/__init__.py
clockwatch/clockwatch.py
clockwatch.egg-info/PKG-INFO
clockwatch.egg-info/SOURCES.txt
clockwatch.egg-info/dependency_links.txt
clockwatch.egg-info/not-zip-safe
clockwatch.egg-info/top_level.txt