Metadata-Version: 1.0
Name: clockwatch
Version: 0.1
Summary: A simple python library for getting relative time.
Home-page: https://github.com/illmawutor/clockwatch
Author: Mawutor C. Agbenyenu
Author-email: cyril.mawutor@gmail.com
License: MIT
Platform: UNKNOWN
